odoo/addons/product_form_purchase_link/README.rst
odoo/addons/product_form_purchase_link/__init__.py
odoo/addons/product_form_purchase_link/__manifest__.py
odoo/addons/product_form_purchase_link/i18n/product_form_purchase_link.pot
odoo/addons/product_form_purchase_link/readme/CONTRIBUTORS.rst
odoo/addons/product_form_purchase_link/readme/DESCRIPTION.rst
odoo/addons/product_form_purchase_link/readme/USAGE.rst
odoo/addons/product_form_purchase_link/static/description/icon.png
odoo/addons/product_form_purchase_link/static/description/index.html
odoo/addons/product_form_purchase_link/views/product_product.xml
odoo/addons/product_form_purchase_link/views/product_template.xml
odoo/addons/product_form_purchase_link/views/purchase_order_line.xml
odoo13_addon_product_form_purchase_link-13.0.1.1.0.dist-info/METADATA
odoo13_addon_product_form_purchase_link-13.0.1.1.0.dist-info/WHEEL
odoo13_addon_product_form_purchase_link-13.0.1.1.0.dist-info/top_level.txt
odoo13_addon_product_form_purchase_link-13.0.1.1.0.dist-info/RECORD
